README.md
setup.py
deos.net.egg-info/PKG-INFO
deos.net.egg-info/SOURCES.txt
deos.net.egg-info/dependency_links.txt
deos.net.egg-info/not-zip-safe
deos.net.egg-info/top_level.txt
deos/net/__init__.py