Metadata-Version: 1.0
Name: deos.net
Version: 0.1
Summary: deos.net
Home-page: https://github.com/desantis/python-deos.net
Author: Andrew T. DeSantis
Author-email: atd@deos.org
License: MIT
Platform: UNKNOWN
